snaek/__init__.py
snaek/_bindgen.py
snaek/_bindgen__ffi.py
snaek/_bindgen__lib.so
snaek/_compat.py
snaek/bindgen.py
snaek/empty.c
snaek/ffi.py
snaek/setuptools_ext.py
snaek-0.2.0.dist-info/DESCRIPTION.rst
snaek-0.2.0.dist-info/METADATA
snaek-0.2.0.dist-info/RECORD
snaek-0.2.0.dist-info/WHEEL
snaek-0.2.0.dist-info/entry_points.txt
snaek-0.2.0.dist-info/metadata.json
snaek-0.2.0.dist-info/top_level.txt
