Metadata-Version: 2.0
Name: snaek
Version: 0.2.0
Summary: A python library for distributing Rust modules.
Home-page: UNKNOWN
Author: Armin Ronacher
Author-email: armin.ronacher@active-4.com
License: UNKNOWN
Platform: any
Classifier: License :: OSI Approved :: Apache Software License
Classifier: Programming Language :: Python
Requires-Dist: cffi (>=1.6.0)
